{
  "meta": {
    "timestamp": "2025-11-23T13:55:43.672Z",
    "epoch": 160,
    "tool_version": "1.0.0"
  },
  "tla_global": {
    "total_tla_value_locked": 2270000,
    "total_tla_rewards_year": 1180000,
    "total_lp_trade_volume": 0
  },
  "dao_tla_deposits": {
    "adao_tla_deposits_usd": 5324,
    "adao_tla_deposits_apr": 61.51,
    "adao_tla_deposits_tokens": [
      {
        "token": "CAPA",
        "amount": 272178.609735228
      },
      {
        "token": "LUNA",
        "amount": 39364.0071525382
      },
      {
        "token": "ROAR",
        "amount": 2033197468.2758417
      },
      {
        "token": "ampLUNA",
        "amount": 11232.458181235594
      },
      {
        "token": "ampCAPA",
        "amount": 304979.260203
      },
      {
        "token": "ampROAR",
        "amount": 506754650.96490794
      },
      {
        "token": "xASTRO",
        "amount": 20705.424186
      }
    ],
    "adao_unclaimed_rewards": {
      "total_usd": 387.5,
      "z_assets": 3637.58,
      "amp_luna": 2812.19
    }
  },
  "liquidity_pools": {
    "active": [
      {
        "liquidity_pool_name": "LUNA-EURe LP",
        "dex_name": "Astroport",
        "pool_type": "pcl",
        "dex_lp_depth": 82730,
        "tla_staked": 77310,
        "percentage_lp_depth_in_tla": 93.44856762963857,
        "lp_apr_non_amplified": "52.74 %",
        "lp_apr_amplified": "64.67",
        "volume_7d": 0,
        "rewards_year": 44130,
        "rewards_epoch": 848.6538461538462,
        "adao_deposits_non_amplified": 0,
        "adao_deposits_amplified": 0,
        "is_inactive": false
      },
      {
        "liquidity_pool_name": "LUNA-USDC LP",
        "dex_name": "Astroport",
        "pool_type": "pcl",
        "dex_lp_depth": 571170,
        "tla_staked": 511210,
        "percentage_lp_depth_in_tla": 89.50224976802002,
        "lp_apr_non_amplified": "76.89 %",
        "lp_apr_amplified": "98.35",
        "volume_7d": 0,
        "rewards_year": 365650,
        "rewards_epoch": 7031.7307692307695,
        "adao_deposits_non_amplified": 0,
        "adao_deposits_amplified": 0,
        "is_inactive": false
      },
      {
        "liquidity_pool_name": "LUNA-USDC LP",
        "dex_name": "WhiteWhale",
        "pool_type": "xyk",
        "dex_lp_depth": 85290,
        "tla_staked": 61570,
        "percentage_lp_depth_in_tla": 72.18900222769375,
        "lp_apr_non_amplified": "84.14 %",
        "lp_apr_amplified": "127.53",
        "volume_7d": 0,
        "rewards_year": 57970,
        "rewards_epoch": 1114.8076923076924,
        "adao_deposits_non_amplified": 0,
        "adao_deposits_amplified": 0,
        "is_inactive": false
      },
      {
        "liquidity_pool_name": "LUNA-USDT LP",
        "dex_name": "Astroport",
        "pool_type": "pcl",
        "dex_lp_depth": 11944.18,
        "tla_staked": 9229.82,
        "percentage_lp_depth_in_tla": 77.27462245210639,
        "lp_apr_non_amplified": "68.78 %",
        "lp_apr_amplified": "84.74",
        "volume_7d": 0,
        "rewards_year": 5887.87,
        "rewards_epoch": 113.22826923076923,
        "adao_deposits_non_amplified": 0,
        "adao_deposits_amplified": 0,
        "is_inactive": false
      },
      {
        "liquidity_pool_name": "LUNA-ASTRO LP",
        "dex_name": "Astroport",
        "pool_type": "pcl",
        "dex_lp_depth": 31540,
        "tla_staked": 30000,
        "percentage_lp_depth_in_tla": 95.11731135066583,
        "lp_apr_non_amplified": "55.52 %",
        "lp_apr_amplified": "69.41",
        "volume_7d": 0,
        "rewards_year": 18150,
        "rewards_epoch": 349.03846153846155,
        "adao_deposits_non_amplified": 0,
        "adao_deposits_amplified": 0,
        "is_inactive": false
      },
      {
        "liquidity_pool_name": "LUNA-CAPA LP",
        "dex_name": "Astroport",
        "pool_type": "pcl",
        "dex_lp_depth": 33960,
        "tla_staked": 32100,
        "percentage_lp_depth_in_tla": 94.52296819787986,
        "lp_apr_non_amplified": "93.37 %",
        "lp_apr_amplified": "148.19",
        "volume_7d": 0,
        "rewards_year": 33110,
        "rewards_epoch": 636.7307692307693,
        "adao_deposits_non_amplified": 265.02,
        "adao_deposits_amplified": 163.63,
        "is_inactive": false
      },
      {
        "liquidity_pool_name": "LUNA-FUEL LP",
        "dex_name": "Astroport",
        "pool_type": "pcl",
        "dex_lp_depth": 32390,
        "tla_staked": 22070,
        "percentage_lp_depth_in_tla": 68.13831429453535,
        "lp_apr_non_amplified": "108.45 %",
        "lp_apr_amplified": "186.86",
        "volume_7d": 0,
        "rewards_year": 26150,
        "rewards_epoch": 502.88461538461536,
        "adao_deposits_non_amplified": 0,
        "adao_deposits_amplified": 0,
        "is_inactive": false
      },
      {
        "liquidity_pool_name": "LUNA-ROAR LP",
        "dex_name": "Astroport",
        "pool_type": "pcl",
        "dex_lp_depth": 20760,
        "tla_staked": 17900,
        "percentage_lp_depth_in_tla": 86.22350674373796,
        "lp_apr_non_amplified": "132.03 %",
        "lp_apr_amplified": "237.58",
        "volume_7d": 0,
        "rewards_year": 23750,
        "rewards_epoch": 456.7307692307692,
        "adao_deposits_non_amplified": 195.07,
        "adao_deposits_amplified": 267.47,
        "is_inactive": false
      },
      {
        "liquidity_pool_name": "LUNA-SOLID LP",
        "dex_name": "Astroport",
        "pool_type": "xyk",
        "dex_lp_depth": 13431.65,
        "tla_staked": 11586.57,
        "percentage_lp_depth_in_tla": 86.26319178954188,
        "lp_apr_non_amplified": "28.97 %",
        "lp_apr_amplified": "30.54",
        "volume_7d": 0,
        "rewards_year": 3365.86,
        "rewards_epoch": 64.72807692307693,
        "adao_deposits_non_amplified": 0,
        "adao_deposits_amplified": 0,
        "is_inactive": false
      },
      {
        "liquidity_pool_name": "LUNA-SWTH LP",
        "dex_name": "Astroport",
        "pool_type": "xyk",
        "dex_lp_depth": 14609.85,
        "tla_staked": 13826.46,
        "percentage_lp_depth_in_tla": 94.63793262764504,
        "lp_apr_non_amplified": "40.33 %",
        "lp_apr_amplified": "48.07",
        "volume_7d": 0,
        "rewards_year": 6717.54,
        "rewards_epoch": 129.18346153846153,
        "adao_deposits_non_amplified": 0,
        "adao_deposits_amplified": 0,
        "is_inactive": false
      },
      {
        "liquidity_pool_name": "LUNA-ampLUNA LP",
        "dex_name": "Astroport",
        "pool_type": "pcl",
        "dex_lp_depth": 218520,
        "tla_staked": 104020,
        "percentage_lp_depth_in_tla": 47.60205015559217,
        "lp_apr_non_amplified": "49.62 %",
        "lp_apr_amplified": "62.34",
        "volume_7d": 0,
        "rewards_year": 60830,
        "rewards_epoch": 1169.8076923076924,
        "adao_deposits_non_amplified": 1741.19,
        "adao_deposits_amplified": 2197.16,
        "is_inactive": false
      },
      {
        "liquidity_pool_name": "LUNA-boneLUNA LP",
        "dex_name": "Astroport",
        "pool_type": "stable",
        "dex_lp_depth": 44980,
        "tla_staked": 42970,
        "percentage_lp_depth_in_tla": 95.53134726545132,
        "lp_apr_non_amplified": "45.16 %",
        "lp_apr_amplified": "56.05",
        "volume_7d": 0,
        "rewards_year": 23700,
        "rewards_epoch": 455.7692307692308,
        "adao_deposits_non_amplified": 0,
        "adao_deposits_amplified": 0,
        "is_inactive": false
      },
      {
        "liquidity_pool_name": "LUNA-boneLUNA LP",
        "dex_name": "WhiteWhale",
        "pool_type": "xyk",
        "dex_lp_depth": 263020,
        "tla_staked": 29500,
        "percentage_lp_depth_in_tla": 11.215877119610676,
        "lp_apr_non_amplified": "13.66 %",
        "lp_apr_amplified": "14.31",
        "volume_7d": 0,
        "rewards_year": 6984.12,
        "rewards_epoch": 134.31,
        "adao_deposits_non_amplified": 0,
        "adao_deposits_amplified": 0,
        "is_inactive": false
      },
      {
        "liquidity_pool_name": "LUNA-stLUNA LP",
        "dex_name": "Astroport",
        "pool_type": "stable",
        "dex_lp_depth": 5806.62,
        "tla_staked": 3767.19,
        "percentage_lp_depth_in_tla": 64.87750188577864,
        "lp_apr_non_amplified": "55.69 %",
        "lp_apr_amplified": "72.91",
        "volume_7d": 0,
        "rewards_year": 2474.75,
        "rewards_epoch": 47.59134615384615,
        "adao_deposits_non_amplified": 0,
        "adao_deposits_amplified": 0,
        "is_inactive": false
      },
      {
        "liquidity_pool_name": "USDC-SOLID LP",
        "dex_name": "Astroport",
        "pool_type": "xyk",
        "dex_lp_depth": 98230,
        "tla_staked": 90410,
        "percentage_lp_depth_in_tla": 92.03909192710984,
        "lp_apr_non_amplified": "27.09 %",
        "lp_apr_amplified": "30.03",
        "volume_7d": 0,
        "rewards_year": 31560,
        "rewards_epoch": 606.9230769230769,
        "adao_deposits_non_amplified": 0,
        "adao_deposits_amplified": 0,
        "is_inactive": false
      },
      {
        "liquidity_pool_name": "LUNA-ATOM LP",
        "dex_name": "Astroport",
        "pool_type": "xyk",
        "dex_lp_depth": 30900,
        "tla_staked": 27690,
        "percentage_lp_depth_in_tla": 89.61165048543688,
        "lp_apr_non_amplified": "47.25 %",
        "lp_apr_amplified": "53.75",
        "volume_7d": 0,
        "rewards_year": 12638.4,
        "rewards_epoch": 243.04615384615383,
        "adao_deposits_non_amplified": 0,
        "adao_deposits_amplified": 0,
        "is_inactive": false
      },
      {
        "liquidity_pool_name": "LUNA-ATOM LP",
        "dex_name": "WhiteWhale",
        "pool_type": "xyk",
        "dex_lp_depth": 11679.79,
        "tla_staked": 9626.03,
        "percentage_lp_depth_in_tla": 82.41612220767668,
        "lp_apr_non_amplified": "47.07 %",
        "lp_apr_amplified": "58.99",
        "volume_7d": 0,
        "rewards_year": 5493.76,
        "rewards_epoch": 105.64923076923077,
        "adao_deposits_non_amplified": 0,
        "adao_deposits_amplified": 0,
        "is_inactive": false
      },
      {
        "liquidity_pool_name": "LUNA-PAXG LP",
        "dex_name": "Astroport",
        "pool_type": "pcl",
        "dex_lp_depth": 77770,
        "tla_staked": 77520,
        "percentage_lp_depth_in_tla": 99.67853928249968,
        "lp_apr_non_amplified": "55.95 %",
        "lp_apr_amplified": "73.35",
        "volume_7d": 0,
        "rewards_year": 51120,
        "rewards_epoch": 983.0769230769231,
        "adao_deposits_non_amplified": 0,
        "adao_deposits_amplified": 0,
        "is_inactive": false
      },
      {
        "liquidity_pool_name": "LUNA-wBTC.atom LP",
        "dex_name": "Astroport",
        "pool_type": "pcl",
        "dex_lp_depth": 83470,
        "tla_staked": 80910,
        "percentage_lp_depth_in_tla": 96.93302983107704,
        "lp_apr_non_amplified": "58.83 %",
        "lp_apr_amplified": "74.95",
        "volume_7d": 0,
        "rewards_year": 51800,
        "rewards_epoch": 996.1538461538462,
        "adao_deposits_non_amplified": 0,
        "adao_deposits_amplified": 0,
        "is_inactive": false
      },
      {
        "liquidity_pool_name": "LUNA-wBTC.axl LP",
        "dex_name": "Astroport",
        "pool_type": "pcl",
        "dex_lp_depth": 75120,
        "tla_staked": 71490,
        "percentage_lp_depth_in_tla": 95.16773162939297,
        "lp_apr_non_amplified": "55.79 %",
        "lp_apr_amplified": "68.78",
        "volume_7d": 0,
        "rewards_year": 42140,
        "rewards_epoch": 810.3846153846154,
        "adao_deposits_non_amplified": 0,
        "adao_deposits_amplified": 0,
        "is_inactive": false
      },
      {
        "liquidity_pool_name": "LUNA-wBTC.osmo LP",
        "dex_name": "WhiteWhale",
        "pool_type": "xyk",
        "dex_lp_depth": 30240,
        "tla_staked": 26240,
        "percentage_lp_depth_in_tla": 86.77248677248677,
        "lp_apr_non_amplified": "58.05 %",
        "lp_apr_amplified": "76.92",
        "volume_7d": 0,
        "rewards_year": 17850,
        "rewards_epoch": 343.2692307692308,
        "adao_deposits_non_amplified": 0,
        "adao_deposits_amplified": 0,
        "is_inactive": false
      },
      {
        "liquidity_pool_name": "LUNA-wstETH LP",
        "dex_name": "Astroport",
        "pool_type": "pcl",
        "dex_lp_depth": 16840,
        "tla_staked": 16660,
        "percentage_lp_depth_in_tla": 98.93111638954869,
        "lp_apr_non_amplified": "61.79 %",
        "lp_apr_amplified": "77.19",
        "volume_7d": 0,
        "rewards_year": 10486.48,
        "rewards_epoch": 201.66307692307691,
        "adao_deposits_non_amplified": 0,
        "adao_deposits_amplified": 0,
        "is_inactive": false
      },
      {
        "liquidity_pool_name": "LUNA-wstETH LP",
        "dex_name": "WhiteWhale",
        "pool_type": "xyk",
        "dex_lp_depth": 24620,
        "tla_staked": 20970,
        "percentage_lp_depth_in_tla": 85.17465475223396,
        "lp_apr_non_amplified": "49.79 %",
        "lp_apr_amplified": "63.28",
        "volume_7d": 0,
        "rewards_year": 12542.19,
        "rewards_epoch": 241.19596153846155,
        "adao_deposits_non_amplified": 0,
        "adao_deposits_amplified": 0,
        "is_inactive": false
      },
      {
        "liquidity_pool_name": "USDC-EURe LP",
        "dex_name": "Astroport",
        "pool_type": "pcl",
        "dex_lp_depth": 236300,
        "tla_staked": 220280,
        "percentage_lp_depth_in_tla": 93.22048243757935,
        "lp_apr_non_amplified": "8.73 %",
        "lp_apr_amplified": "8.52",
        "volume_7d": 0,
        "rewards_year": 32720,
        "rewards_epoch": 629.2307692307693,
        "adao_deposits_non_amplified": 0,
        "adao_deposits_amplified": 0,
        "is_inactive": false
      },
      {
        "liquidity_pool_name": "ATOM-dATOM LP",
        "dex_name": "Astroport",
        "pool_type": "pcl",
        "dex_lp_depth": 250620,
        "tla_staked": 39190,
        "percentage_lp_depth_in_tla": 15.637219695156013,
        "lp_apr_non_amplified": "22.03 %",
        "lp_apr_amplified": "24.07",
        "volume_7d": 0,
        "rewards_year": 12227.48,
        "rewards_epoch": 235.14384615384614,
        "adao_deposits_non_amplified": 0,
        "adao_deposits_amplified": 0,
        "is_inactive": false
      },
      {
        "liquidity_pool_name": "LUNA-arbLUNA LP",
        "dex_name": "Astroport",
        "pool_type": "pcl",
        "dex_lp_depth": 47160,
        "tla_staked": 46170,
        "percentage_lp_depth_in_tla": 97.90076335877863,
        "lp_apr_non_amplified": "46.66 %",
        "lp_apr_amplified": "58.36",
        "volume_7d": 0,
        "rewards_year": 26160,
        "rewards_epoch": 503.0769230769231,
        "adao_deposits_non_amplified": 0,
        "adao_deposits_amplified": 0,
        "is_inactive": false
      },
      {
        "liquidity_pool_name": "USDC-USDT LP",
        "dex_name": "Astroport",
        "pool_type": "stable",
        "dex_lp_depth": 224010,
        "tla_staked": 189890,
        "percentage_lp_depth_in_tla": 84.76853711887861,
        "lp_apr_non_amplified": "3.77 %",
        "lp_apr_amplified": "3.50",
        "volume_7d": 0,
        "rewards_year": 25840,
        "rewards_epoch": 496.9230769230769,
        "adao_deposits_non_amplified": 0,
        "adao_deposits_amplified": 0,
        "is_inactive": false
      },
      {
        "liquidity_pool_name": "ampCAPA",
        "dex_name": "Single",
        "pool_type": "single",
        "dex_lp_depth": 101680,
        "tla_staked": 90700,
        "percentage_lp_depth_in_tla": 89.20141620771047,
        "lp_apr_non_amplified": "55.16 %",
        "lp_apr_amplified": "69.03",
        "volume_7d": 0,
        "rewards_year": 54820,
        "rewards_epoch": 1054.2307692307693,
        "adao_deposits_non_amplified": 0,
        "adao_deposits_amplified": 264.13,
        "is_inactive": false
      },
      {
        "liquidity_pool_name": "ampROAR-ROAR LP",
        "dex_name": "WhiteWhale",
        "pool_type": "xyk",
        "dex_lp_depth": 33070,
        "tla_staked": 30010,
        "percentage_lp_depth_in_tla": 90.74690051406108,
        "lp_apr_non_amplified": "84.54 %",
        "lp_apr_amplified": "128.39",
        "volume_7d": 0,
        "rewards_year": 28380,
        "rewards_epoch": 545.7692307692307,
        "adao_deposits_non_amplified": 74.31,
        "adao_deposits_amplified": 96.89,
        "is_inactive": false
      },
      {
        "liquidity_pool_name": "wBTC.axl-wBTC.osmo LP",
        "dex_name": "Astroport",
        "pool_type": "stable",
        "dex_lp_depth": 106310,
        "tla_staked": 94320,
        "percentage_lp_depth_in_tla": 88.72166306085974,
        "lp_apr_non_amplified": "16.94 %",
        "lp_apr_amplified": "18.04",
        "volume_7d": 0,
        "rewards_year": 25000,
        "rewards_epoch": 480.7692307692308,
        "adao_deposits_non_amplified": 0,
        "adao_deposits_amplified": 0,
        "is_inactive": false
      },
      {
        "liquidity_pool_name": "wBTC.osmo-wBTC.axl LP",
        "dex_name": "WhiteWhale",
        "pool_type": "stable",
        "dex_lp_depth": 100230,
        "tla_staked": 81530,
        "percentage_lp_depth_in_tla": 81.3429113040008,
        "lp_apr_non_amplified": "18.60 %",
        "lp_apr_amplified": "20.08",
        "volume_7d": 0,
        "rewards_year": 23320,
        "rewards_epoch": 448.46153846153845,
        "adao_deposits_non_amplified": 0,
        "adao_deposits_amplified": 0,
        "is_inactive": false
      },
      {
        "liquidity_pool_name": "wstETH-wETH.axl LP",
        "dex_name": "Astroport",
        "pool_type": "xyk",
        "dex_lp_depth": 64280,
        "tla_staked": 61620,
        "percentage_lp_depth_in_tla": 95.86185438705662,
        "lp_apr_non_amplified": "50.09 %",
        "lp_apr_amplified": "63.62",
        "volume_7d": 0,
        "rewards_year": 36890,
        "rewards_epoch": 709.4230769230769,
        "adao_deposits_non_amplified": 0,
        "adao_deposits_amplified": 0,
        "is_inactive": false
      },
      {
        "liquidity_pool_name": "xASTRO",
        "dex_name": "Single",
        "pool_type": "single",
        "dex_lp_depth": 818050,
        "tla_staked": 13890.99,
        "percentage_lp_depth_in_tla": 1.6980612432002933,
        "lp_apr_non_amplified": "32.97 %",
        "lp_apr_amplified": null,
        "volume_7d": 0,
        "rewards_year": 4156.43,
        "rewards_epoch": 79.93134615384616,
        "adao_deposits_non_amplified": 59.09,
        "adao_deposits_amplified": 0,
        "is_inactive": false
      }
    ],
    "inactive": [
      {
        "liquidity_pool_name": "LUNA-EURe LP",
        "dex_name": "WhiteWhale",
        "pool_type": "xyk",
        "dex_lp_depth": 3712.49,
        "tla_staked": 1586.5,
        "percentage_lp_depth_in_tla": 42.734121842752444,
        "lp_apr_non_amplified": "-10.00 %",
        "lp_apr_amplified": "-10.00",
        "volume_7d": 0,
        "rewards_year": 0,
        "rewards_epoch": 0,
        "adao_deposits_non_amplified": 0,
        "adao_deposits_amplified": 0,
        "is_inactive": true
      },
      {
        "liquidity_pool_name": "LUNA-SOLID LP",
        "dex_name": "Astroport",
        "pool_type": "xyk",
        "dex_lp_depth": 13431.65,
        "tla_staked": 0,
        "percentage_lp_depth_in_tla": 0,
        "lp_apr_non_amplified": "-0.07 %",
        "lp_apr_amplified": null,
        "volume_7d": 0,
        "rewards_year": 0,
        "rewards_epoch": 0,
        "adao_deposits_non_amplified": 0,
        "adao_deposits_amplified": 0,
        "is_inactive": true
      },
      {
        "liquidity_pool_name": "LUNA-SOLID LP",
        "dex_name": "WhiteWhale",
        "pool_type": "xyk",
        "dex_lp_depth": 91.9,
        "tla_staked": 0,
        "percentage_lp_depth_in_tla": 0,
        "lp_apr_non_amplified": "-10.00 %",
        "lp_apr_amplified": null,
        "volume_7d": 0,
        "rewards_year": 0,
        "rewards_epoch": 0,
        "adao_deposits_non_amplified": 0,
        "adao_deposits_amplified": 0,
        "is_inactive": true
      },
      {
        "liquidity_pool_name": "LUNA-USDC LP",
        "dex_name": "Astroport",
        "pool_type": "xyk",
        "dex_lp_depth": 0.01,
        "tla_staked": 0,
        "percentage_lp_depth_in_tla": 0,
        "lp_apr_non_amplified": "-10.00 %",
        "lp_apr_amplified": null,
        "volume_7d": 0,
        "rewards_year": 0,
        "rewards_epoch": 0,
        "adao_deposits_non_amplified": 0,
        "adao_deposits_amplified": 0,
        "is_inactive": true
      },
      {
        "liquidity_pool_name": "LUNA-USDT LP",
        "dex_name": "WhiteWhale",
        "pool_type": "xyk",
        "dex_lp_depth": 6772.19,
        "tla_staked": 14.79,
        "percentage_lp_depth_in_tla": 0.21839316380668586,
        "lp_apr_non_amplified": "-10.00 %",
        "lp_apr_amplified": "-10.00",
        "volume_7d": 0,
        "rewards_year": 0,
        "rewards_epoch": 0,
        "adao_deposits_non_amplified": 0,
        "adao_deposits_amplified": 0,
        "is_inactive": true
      },
      {
        "liquidity_pool_name": "LUNA-ASTRO LP",
        "dex_name": "WhiteWhale",
        "pool_type": "xyk",
        "dex_lp_depth": 2.66,
        "tla_staked": 0.01,
        "percentage_lp_depth_in_tla": 0.37593984962406013,
        "lp_apr_non_amplified": "-10.00 %",
        "lp_apr_amplified": null,
        "volume_7d": 0,
        "rewards_year": 0,
        "rewards_epoch": 0,
        "adao_deposits_non_amplified": 0,
        "adao_deposits_amplified": 0,
        "is_inactive": true
      },
      {
        "liquidity_pool_name": "LUNA-CAPA LP",
        "dex_name": "WhiteWhale",
        "pool_type": "xyk",
        "dex_lp_depth": 644.37,
        "tla_staked": 273.22,
        "percentage_lp_depth_in_tla": 42.401104955227595,
        "lp_apr_non_amplified": "-10.00 %",
        "lp_apr_amplified": "-10.00",
        "volume_7d": 0,
        "rewards_year": 0,
        "rewards_epoch": 0,
        "adao_deposits_non_amplified": 0,
        "adao_deposits_amplified": 0,
        "is_inactive": true
      },
      {
        "liquidity_pool_name": "LUNA-ROAR LP",
        "dex_name": "WhiteWhale",
        "pool_type": "xyk",
        "dex_lp_depth": 85.87,
        "tla_staked": 0.01,
        "percentage_lp_depth_in_tla": 0.01164551065564225,
        "lp_apr_non_amplified": "-10.00 %",
        "lp_apr_amplified": "-10.00",
        "volume_7d": 0,
        "rewards_year": 0,
        "rewards_epoch": 0,
        "adao_deposits_non_amplified": 0,
        "adao_deposits_amplified": 0,
        "is_inactive": true
      },
      {
        "liquidity_pool_name": "LUNA-SOLID LP",
        "dex_name": "WhiteWhale",
        "pool_type": "xyk",
        "dex_lp_depth": 91.9,
        "tla_staked": 0.06,
        "percentage_lp_depth_in_tla": 0.06528835690968443,
        "lp_apr_non_amplified": "-10.00 %",
        "lp_apr_amplified": "-10.00",
        "volume_7d": 0,
        "rewards_year": 0,
        "rewards_epoch": 0,
        "adao_deposits_non_amplified": 0,
        "adao_deposits_amplified": 0,
        "is_inactive": true
      },
      {
        "liquidity_pool_name": "LUNA-SWTH LP",
        "dex_name": "WhiteWhale",
        "pool_type": "xyk",
        "dex_lp_depth": 1.53,
        "tla_staked": 0.01,
        "percentage_lp_depth_in_tla": 0.6535947712418301,
        "lp_apr_non_amplified": "-10.00 %",
        "lp_apr_amplified": null,
        "volume_7d": 0,
        "rewards_year": 0,
        "rewards_epoch": 0,
        "adao_deposits_non_amplified": 0,
        "adao_deposits_amplified": 0,
        "is_inactive": true
      },
      {
        "liquidity_pool_name": "LUNA-Whale LP",
        "dex_name": "Astroport",
        "pool_type": "stable",
        "dex_lp_depth": 0.01,
        "tla_staked": 0,
        "percentage_lp_depth_in_tla": 0,
        "lp_apr_non_amplified": "-10.00 %",
        "lp_apr_amplified": null,
        "volume_7d": 0,
        "rewards_year": 0,
        "rewards_epoch": 0,
        "adao_deposits_non_amplified": 0,
        "adao_deposits_amplified": 0,
        "is_inactive": true
      },
      {
        "liquidity_pool_name": "LUNA-Whale LP",
        "dex_name": "Astroport",
        "pool_type": "pcl",
        "dex_lp_depth": 4.38,
        "tla_staked": 0.01,
        "percentage_lp_depth_in_tla": 0.22831050228310507,
        "lp_apr_non_amplified": "-3.38 %",
        "lp_apr_amplified": "-3.38",
        "volume_7d": 0,
        "rewards_year": 0,
        "rewards_epoch": 0,
        "adao_deposits_non_amplified": 0,
        "adao_deposits_amplified": 0,
        "is_inactive": true
      },
      {
        "liquidity_pool_name": "LUNA-Whale LP",
        "dex_name": "WhiteWhale",
        "pool_type": "xyk",
        "dex_lp_depth": 502.96,
        "tla_staked": 32.6,
        "percentage_lp_depth_in_tla": 6.481628757754096,
        "lp_apr_non_amplified": "-10.00 %",
        "lp_apr_amplified": "-10.00",
        "volume_7d": 0,
        "rewards_year": 0,
        "rewards_epoch": 0,
        "adao_deposits_non_amplified": 0,
        "adao_deposits_amplified": 0,
        "is_inactive": true
      },
      {
        "liquidity_pool_name": "LUNA-ampLUNA LP",
        "dex_name": "WhiteWhale",
        "pool_type": "xyk",
        "dex_lp_depth": 118500,
        "tla_staked": 379.58,
        "percentage_lp_depth_in_tla": 0.32032067510548523,
        "lp_apr_non_amplified": "-10.00 %",
        "lp_apr_amplified": "-10.00",
        "volume_7d": 0,
        "rewards_year": 0,
        "rewards_epoch": 0,
        "adao_deposits_non_amplified": 0,
        "adao_deposits_amplified": 0,
        "is_inactive": true
      },
      {
        "liquidity_pool_name": "LUNA-stLUNA LP",
        "dex_name": "WhiteWhale",
        "pool_type": "xyk",
        "dex_lp_depth": 1.73,
        "tla_staked": 0.01,
        "percentage_lp_depth_in_tla": 0.5780346820809249,
        "lp_apr_non_amplified": "-10.00 %",
        "lp_apr_amplified": null,
        "volume_7d": 0,
        "rewards_year": 0,
        "rewards_epoch": 0,
        "adao_deposits_non_amplified": 0,
        "adao_deposits_amplified": 0,
        "is_inactive": true
      },
      {
        "liquidity_pool_name": "USDC-SOLID LP",
        "dex_name": "WhiteWhale",
        "pool_type": "xyk",
        "dex_lp_depth": 419.65,
        "tla_staked": 0.01,
        "percentage_lp_depth_in_tla": 0.0023829381627546767,
        "lp_apr_non_amplified": "-10.00 %",
        "lp_apr_amplified": "-10.00",
        "volume_7d": 0,
        "rewards_year": 0,
        "rewards_epoch": 0,
        "adao_deposits_non_amplified": 0,
        "adao_deposits_amplified": 0,
        "is_inactive": true
      },
      {
        "liquidity_pool_name": "LUNA-INJ LP",
        "dex_name": "Astroport",
        "pool_type": "xyk",
        "dex_lp_depth": 1296.34,
        "tla_staked": 60.58,
        "percentage_lp_depth_in_tla": 4.6731567335729824,
        "lp_apr_non_amplified": "-3.09 %",
        "lp_apr_amplified": "-3.09",
        "volume_7d": 0,
        "rewards_year": 0,
        "rewards_epoch": 0,
        "adao_deposits_non_amplified": 0,
        "adao_deposits_amplified": 0,
        "is_inactive": true
      },
      {
        "liquidity_pool_name": "LUNA-INJ LP",
        "dex_name": "WhiteWhale",
        "pool_type": "xyk",
        "dex_lp_depth": 1817.7,
        "tla_staked": 1034.58,
        "percentage_lp_depth_in_tla": 56.91698300049512,
        "lp_apr_non_amplified": "-10.00 %",
        "lp_apr_amplified": "-10.00",
        "volume_7d": 0,
        "rewards_year": 0,
        "rewards_epoch": 0,
        "adao_deposits_non_amplified": 0,
        "adao_deposits_amplified": 0,
        "is_inactive": true
      },
      {
        "liquidity_pool_name": "LUNA-wBNB LP",
        "dex_name": "Astroport",
        "pool_type": "pcl",
        "dex_lp_depth": 36.64,
        "tla_staked": 12.08,
        "percentage_lp_depth_in_tla": 32.96943231441048,
        "lp_apr_non_amplified": "-10.00 %",
        "lp_apr_amplified": "-10.00",
        "volume_7d": 0,
        "rewards_year": 0,
        "rewards_epoch": 0,
        "adao_deposits_non_amplified": 0,
        "adao_deposits_amplified": 0,
        "is_inactive": true
      },
      {
        "liquidity_pool_name": "LUNA-wBNB LP",
        "dex_name": "WhiteWhale",
        "pool_type": "xyk",
        "dex_lp_depth": 0.01,
        "tla_staked": 0.01,
        "percentage_lp_depth_in_tla": 100,
        "lp_apr_non_amplified": "-10.00 %",
        "lp_apr_amplified": null,
        "volume_7d": 0,
        "rewards_year": 0,
        "rewards_epoch": 0,
        "adao_deposits_non_amplified": 0,
        "adao_deposits_amplified": 0,
        "is_inactive": true
      },
      {
        "liquidity_pool_name": "LUNA-wBNB.axl LP",
        "dex_name": "Astroport",
        "pool_type": "pcl",
        "dex_lp_depth": 688.18,
        "tla_staked": 1.01,
        "percentage_lp_depth_in_tla": 0.14676392804208202,
        "lp_apr_non_amplified": "-10.00 %",
        "lp_apr_amplified": "-10.00",
        "volume_7d": 0,
        "rewards_year": 0,
        "rewards_epoch": 0,
        "adao_deposits_non_amplified": 0,
        "adao_deposits_amplified": 0,
        "is_inactive": true
      },
      {
        "liquidity_pool_name": "LUNA-wBTC.atom LP",
        "dex_name": "Astroport",
        "pool_type": "pcl",
        "dex_lp_depth": 427.82,
        "tla_staked": 0.01,
        "percentage_lp_depth_in_tla": 0.002337431630124819,
        "lp_apr_non_amplified": "-7.07 %",
        "lp_apr_amplified": "-7.07",
        "volume_7d": 0,
        "rewards_year": 0,
        "rewards_epoch": 0,
        "adao_deposits_non_amplified": 0,
        "adao_deposits_amplified": 0,
        "is_inactive": true
      },
      {
        "liquidity_pool_name": "LUNA-wSOL.wh LP",
        "dex_name": "Astroport",
        "pool_type": "pcl",
        "dex_lp_depth": 845.79,
        "tla_staked": 786.21,
        "percentage_lp_depth_in_tla": 92.95569822296315,
        "lp_apr_non_amplified": "-9.97 %",
        "lp_apr_amplified": "-9.97",
        "volume_7d": 0,
        "rewards_year": 0,
        "rewards_epoch": 0,
        "adao_deposits_non_amplified": 0,
        "adao_deposits_amplified": 0,
        "is_inactive": true
      },
      {
        "liquidity_pool_name": "LUNA-wSOL.wh LP",
        "dex_name": "WhiteWhale",
        "pool_type": "xyk",
        "dex_lp_depth": 901.5,
        "tla_staked": 7.4,
        "percentage_lp_depth_in_tla": 0.8208541320022186,
        "lp_apr_non_amplified": "-10.00 %",
        "lp_apr_amplified": "-10.00",
        "volume_7d": 0,
        "rewards_year": 0,
        "rewards_epoch": 0,
        "adao_deposits_non_amplified": 0,
        "adao_deposits_amplified": 0,
        "is_inactive": true
      },
      {
        "liquidity_pool_name": "USDC-EURe LP",
        "dex_name": "WhiteWhale",
        "pool_type": "xyk",
        "dex_lp_depth": 4193.24,
        "tla_staked": 2619.26,
        "percentage_lp_depth_in_tla": 62.46387042000936,
        "lp_apr_non_amplified": "-10.00 %",
        "lp_apr_amplified": "-10.00",
        "volume_7d": 0,
        "rewards_year": 0,
        "rewards_epoch": 0,
        "adao_deposits_non_amplified": 0,
        "adao_deposits_amplified": 0,
        "is_inactive": true
      },
      {
        "liquidity_pool_name": "USDC-USDT LP",
        "dex_name": "Astroport",
        "pool_type": "stable",
        "dex_lp_depth": 224010,
        "tla_staked": 416.67,
        "percentage_lp_depth_in_tla": 0.1860050890585242,
        "lp_apr_non_amplified": "-9.83 %",
        "lp_apr_amplified": "-9.83",
        "volume_7d": 0,
        "rewards_year": 0,
        "rewards_epoch": 0,
        "adao_deposits_non_amplified": 0,
        "adao_deposits_amplified": 0,
        "is_inactive": true
      },
      {
        "liquidity_pool_name": "USDC-USDT LP",
        "dex_name": "WhiteWhale",
        "pool_type": "stable",
        "dex_lp_depth": 2973.8,
        "tla_staked": 481.54,
        "percentage_lp_depth_in_tla": 16.192750016813502,
        "lp_apr_non_amplified": "-10.00 %",
        "lp_apr_amplified": "-10.00",
        "volume_7d": 0,
        "rewards_year": 0,
        "rewards_epoch": 0,
        "adao_deposits_non_amplified": 0,
        "adao_deposits_amplified": 0,
        "is_inactive": true
      },
      {
        "liquidity_pool_name": "USDC-USDT LP",
        "dex_name": "WhiteWhale",
        "pool_type": "xyk",
        "dex_lp_depth": 3721.34,
        "tla_staked": 0.34,
        "percentage_lp_depth_in_tla": 0.009136493843615473,
        "lp_apr_non_amplified": "-10.00 %",
        "lp_apr_amplified": "-10.00",
        "volume_7d": 0,
        "rewards_year": 0,
        "rewards_epoch": 0,
        "adao_deposits_non_amplified": 0,
        "adao_deposits_amplified": 0,
        "is_inactive": true
      },
      {
        "liquidity_pool_name": "ATOM-dATOM LP",
        "dex_name": "WhiteWhale",
        "pool_type": "xyk",
        "dex_lp_depth": 3905.58,
        "tla_staked": 556.88,
        "percentage_lp_depth_in_tla": 14.258573630549112,
        "lp_apr_non_amplified": "-10.00 %",
        "lp_apr_amplified": "-10.00",
        "volume_7d": 0,
        "rewards_year": 0,
        "rewards_epoch": 0,
        "adao_deposits_non_amplified": 0,
        "adao_deposits_amplified": 0,
        "is_inactive": true
      },
      {
        "liquidity_pool_name": "ATOM-stATOM LP",
        "dex_name": "Astroport",
        "pool_type": "pcl",
        "dex_lp_depth": 1527.26,
        "tla_staked": 0.01,
        "percentage_lp_depth_in_tla": 0.0006547673611565811,
        "lp_apr_non_amplified": "-9.63 %",
        "lp_apr_amplified": "-9.63",
        "volume_7d": 0,
        "rewards_year": 0,
        "rewards_epoch": 0,
        "adao_deposits_non_amplified": 0,
        "adao_deposits_amplified": 0,
        "is_inactive": true
      },
      {
        "liquidity_pool_name": "ATOM-stATOM LP",
        "dex_name": "WhiteWhale",
        "pool_type": "xyk",
        "dex_lp_depth": 0.01,
        "tla_staked": 0,
        "percentage_lp_depth_in_tla": 0,
        "lp_apr_non_amplified": "-10.00 %",
        "lp_apr_amplified": null,
        "volume_7d": 0,
        "rewards_year": 0,
        "rewards_epoch": 0,
        "adao_deposits_non_amplified": 0,
        "adao_deposits_amplified": 0,
        "is_inactive": true
      },
      {
        "liquidity_pool_name": "LUNA-arbLUNA LP",
        "dex_name": "Astroport",
        "pool_type": "stable",
        "dex_lp_depth": 13993.75,
        "tla_staked": 11728.71,
        "percentage_lp_depth_in_tla": 83.81391692719964,
        "lp_apr_non_amplified": "-10.00 %",
        "lp_apr_amplified": "-10.00",
        "volume_7d": 0,
        "rewards_year": 0,
        "rewards_epoch": 0,
        "adao_deposits_non_amplified": 0,
        "adao_deposits_amplified": 0,
        "is_inactive": true
      },
      {
        "liquidity_pool_name": "LUNA-arbLUNA LP",
        "dex_name": "WhiteWhale",
        "pool_type": "xyk",
        "dex_lp_depth": 3223.41,
        "tla_staked": 1616.39,
        "percentage_lp_depth_in_tla": 50.145342975296344,
        "lp_apr_non_amplified": "-10.00 %",
        "lp_apr_amplified": "-10.00",
        "volume_7d": 0,
        "rewards_year": 0,
        "rewards_epoch": 0,
        "adao_deposits_non_amplified": 0,
        "adao_deposits_amplified": 0,
        "is_inactive": true
      },
      {
        "liquidity_pool_name": "SWTH-rSWTH LP",
        "dex_name": "Astroport",
        "pool_type": "xyk",
        "dex_lp_depth": 3063.57,
        "tla_staked": 330.41,
        "percentage_lp_depth_in_tla": 10.78512976690593,
        "lp_apr_non_amplified": "-10.00 %",
        "lp_apr_amplified": null,
        "volume_7d": 0,
        "rewards_year": 0,
        "rewards_epoch": 0,
        "adao_deposits_non_amplified": 0,
        "adao_deposits_amplified": 0,
        "is_inactive": true
      },
      {
        "liquidity_pool_name": "SWTH-rSWTH LP",
        "dex_name": "WhiteWhale",
        "pool_type": "xyk",
        "dex_lp_depth": 0.01,
        "tla_staked": 0,
        "percentage_lp_depth_in_tla": 0,
        "lp_apr_non_amplified": "-10.00 %",
        "lp_apr_amplified": null,
        "volume_7d": 0,
        "rewards_year": 0,
        "rewards_epoch": 0,
        "adao_deposits_non_amplified": 0,
        "adao_deposits_amplified": 0,
        "is_inactive": true
      },
      {
        "liquidity_pool_name": "USDC-USDT LP",
        "dex_name": "WhiteWhale",
        "pool_type": "stable",
        "dex_lp_depth": 2973.8,
        "tla_staked": 0,
        "percentage_lp_depth_in_tla": 0,
        "lp_apr_non_amplified": "-10.00 %",
        "lp_apr_amplified": null,
        "volume_7d": 0,
        "rewards_year": 0,
        "rewards_epoch": 0,
        "adao_deposits_non_amplified": 0,
        "adao_deposits_amplified": 0,
        "is_inactive": true
      },
      {
        "liquidity_pool_name": "USDC-USDT LP",
        "dex_name": "WhiteWhale",
        "pool_type": "xyk",
        "dex_lp_depth": 3721.34,
        "tla_staked": 0,
        "percentage_lp_depth_in_tla": 0,
        "lp_apr_non_amplified": "-10.00 %",
        "lp_apr_amplified": null,
        "volume_7d": 0,
        "rewards_year": 0,
        "rewards_epoch": 0,
        "adao_deposits_non_amplified": 0,
        "adao_deposits_amplified": 0,
        "is_inactive": true
      },
      {
        "liquidity_pool_name": "Whale-ampWHALE LP",
        "dex_name": "Astroport",
        "pool_type": "xyk",
        "dex_lp_depth": 5.66,
        "tla_staked": 0.01,
        "percentage_lp_depth_in_tla": 0.17667844522968199,
        "lp_apr_non_amplified": "-10.00 %",
        "lp_apr_amplified": "-10.00",
        "volume_7d": 0,
        "rewards_year": 0,
        "rewards_epoch": 0,
        "adao_deposits_non_amplified": 0,
        "adao_deposits_amplified": 0,
        "is_inactive": true
      },
      {
        "liquidity_pool_name": "Whale-boneWHALE LP",
        "dex_name": "Astroport",
        "pool_type": "xyk",
        "dex_lp_depth": 6.44,
        "tla_staked": 0.01,
        "percentage_lp_depth_in_tla": 0.15527950310559005,
        "lp_apr_non_amplified": "-10.00 %",
        "lp_apr_amplified": "-10.00",
        "volume_7d": 0,
        "rewards_year": 0,
        "rewards_epoch": 0,
        "adao_deposits_non_amplified": 0,
        "adao_deposits_amplified": 0,
        "is_inactive": true
      },
      {
        "liquidity_pool_name": "ampROAR-ROAR LP",
        "dex_name": "Astroport",
        "pool_type": "pcl",
        "dex_lp_depth": 0.01,
        "tla_staked": 0,
        "percentage_lp_depth_in_tla": 0,
        "lp_apr_non_amplified": "-10.00 %",
        "lp_apr_amplified": null,
        "volume_7d": 0,
        "rewards_year": 0,
        "rewards_epoch": 0,
        "adao_deposits_non_amplified": 0,
        "adao_deposits_amplified": 0,
        "is_inactive": true
      },
      {
        "liquidity_pool_name": "ampWHALE-Whale LP",
        "dex_name": "WhiteWhale",
        "pool_type": "xyk",
        "dex_lp_depth": 332.02,
        "tla_staked": 35.92,
        "percentage_lp_depth_in_tla": 10.818625384013012,
        "lp_apr_non_amplified": "-10.00 %",
        "lp_apr_amplified": "-10.00",
        "volume_7d": 0,
        "rewards_year": 0,
        "rewards_epoch": 0,
        "adao_deposits_non_amplified": 0,
        "adao_deposits_amplified": 0,
        "is_inactive": true
      },
      {
        "liquidity_pool_name": "boneWHALE-Whale LP",
        "dex_name": "WhiteWhale",
        "pool_type": "xyk",
        "dex_lp_depth": 314.44,
        "tla_staked": 88.99,
        "percentage_lp_depth_in_tla": 28.301106729423736,
        "lp_apr_non_amplified": "-10.00 %",
        "lp_apr_amplified": "-10.00",
        "volume_7d": 0,
        "rewards_year": 0,
        "rewards_epoch": 0,
        "adao_deposits_non_amplified": 0,
        "adao_deposits_amplified": 0,
        "is_inactive": true
      },
      {
        "liquidity_pool_name": "wETH-wstETH LP",
        "dex_name": "WhiteWhale",
        "pool_type": "xyk",
        "dex_lp_depth": 112.38,
        "tla_staked": 0.01,
        "percentage_lp_depth_in_tla": 0.008898380494749957,
        "lp_apr_non_amplified": "-10.00 %",
        "lp_apr_amplified": "-10.00",
        "volume_7d": 0,
        "rewards_year": 0,
        "rewards_epoch": 0,
        "adao_deposits_non_amplified": 0,
        "adao_deposits_amplified": 0,
        "is_inactive": true
      }
    ]
  },
  "vote_data": {
    "epoch": 160,
    "ends_in": "0 days",
    "adao_rebase": 352.79,
    "adao_unclaimed_rewards": 371.37,
    "pools": [
      {
        "pool_name": "LUNA-EURe LP",
        "dex": "Astroport",
        "bucket": "STABLE",
        "tla_total_votes": 1870000,
        "tla_vote_share": "9.2",
        "pool_depth": 82730,
        "pd_bribes": 0,
        "other_bribes": 0,
        "total_bribes": 0,
        "v_apr": "0 %",
        "adao_vote_vp": 12458.31,
        "adao_vote_share": "1.95"
      },
      {
        "pool_name": "LUNA-EURe LP",
        "dex": "WhiteWhale",
        "bucket": "STABLE",
        "tla_total_votes": 18200,
        "tla_vote_share": "0.1",
        "pool_depth": 3712.49,
        "pd_bribes": 0,
        "other_bribes": 0,
        "total_bribes": 0,
        "v_apr": "0 %",
        "adao_vote_vp": 0,
        "adao_vote_share": "0.00"
      },
      {
        "pool_name": "LUNA-USDC LP",
        "dex": "Astroport",
        "bucket": "STABLE",
        "tla_total_votes": 15690000,
        "tla_vote_share": "76.7",
        "pool_depth": 571170,
        "pd_bribes": 0,
        "other_bribes": 40.54,
        "total_bribes": 40.54,
        "v_apr": "1.82 %",
        "adao_vote_vp": 550720,
        "adao_vote_share": "86.20"
      },
      {
        "pool_name": "LUNA-USDC LP",
        "dex": "WhiteWhale",
        "bucket": "STABLE",
        "tla_total_votes": 2460000,
        "tla_vote_share": "12.1",
        "pool_depth": 85290,
        "pd_bribes": 0,
        "other_bribes": 0,
        "total_bribes": 0,
        "v_apr": "0 %",
        "adao_vote_vp": 0,
        "adao_vote_share": "0.00"
      },
      {
        "pool_name": "LUNA-USDT LP",
        "dex": "Astroport",
        "bucket": "STABLE",
        "tla_total_votes": 249060,
        "tla_vote_share": "1.2",
        "pool_depth": 11944.18,
        "pd_bribes": 0,
        "other_bribes": 0,
        "total_bribes": 0,
        "v_apr": "0 %",
        "adao_vote_vp": 75700,
        "adao_vote_share": "11.85"
      },
      {
        "pool_name": "LUNA-USDT LP",
        "dex": "WhiteWhale",
        "bucket": "STABLE",
        "tla_total_votes": 149040,
        "tla_vote_share": "0.7",
        "pool_depth": 6772.19,
        "pd_bribes": 0,
        "other_bribes": 0,
        "total_bribes": 0,
        "v_apr": "0 %",
        "adao_vote_vp": 0,
        "adao_vote_share": "0.00"
      },
      {
        "pool_name": "LUNA-ASTRO LP",
        "dex": "Astroport",
        "bucket": "PROJECT",
        "tla_total_votes": 1460000,
        "tla_vote_share": "7.4",
        "pool_depth": 31540,
        "pd_bribes": 50,
        "other_bribes": 0,
        "total_bribes": 50,
        "v_apr": "3.39 %",
        "adao_vote_vp": 152050,
        "adao_vote_share": "23.80"
      },
      {
        "pool_name": "LUNA-ASTRO LP",
        "dex": "WhiteWhale",
        "bucket": "PROJECT",
        "tla_total_votes": 1.34,
        "tla_vote_share": "0.0",
        "pool_depth": 2.66,
        "pd_bribes": 50,
        "other_bribes": 0,
        "total_bribes": 50,
        "v_apr": "0 %",
        "adao_vote_vp": 0,
        "adao_vote_share": "0.00"
      },
      {
        "pool_name": "LUNA-CAPA LP",
        "dex": "Astroport",
        "bucket": "PROJECT",
        "tla_total_votes": 2890000,
        "tla_vote_share": "14.7",
        "pool_depth": 33960,
        "pd_bribes": 0,
        "other_bribes": 78.33,
        "total_bribes": 78.33,
        "v_apr": "1.90-19.09 %",
        "adao_vote_vp": 0,
        "adao_vote_share": "0.00"
      },
      {
        "pool_name": "LUNA-CAPA LP",
        "dex": "WhiteWhale",
        "bucket": "PROJECT",
        "tla_total_votes": 19990,
        "tla_vote_share": "0.1",
        "pool_depth": 644.37,
        "pd_bribes": 0,
        "other_bribes": 0,
        "total_bribes": 0,
        "v_apr": "0 %",
        "adao_vote_vp": 0,
        "adao_vote_share": "0.00"
      },
      {
        "pool_name": "LUNA-FUEL LP",
        "dex": "Astroport",
        "bucket": "PROJECT",
        "tla_total_votes": 2040000,
        "tla_vote_share": "10.3",
        "pool_depth": 32390,
        "pd_bribes": 50,
        "other_bribes": 3.030000000000001,
        "total_bribes": 53.03,
        "v_apr": "1.83-18.35 %",
        "adao_vote_vp": 0,
        "adao_vote_share": "0.00"
      },
      {
        "pool_name": "LUNA-ROAR LP",
        "dex": "Astroport",
        "bucket": "PROJECT",
        "tla_total_votes": 1960000,
        "tla_vote_share": "9.9",
        "pool_depth": 20760,
        "pd_bribes": 0,
        "other_bribes": 0,
        "total_bribes": 0,
        "v_apr": "0 %",
        "adao_vote_vp": 22040,
        "adao_vote_share": "3.45"
      },
      {
        "pool_name": "LUNA-ROAR LP",
        "dex": "WhiteWhale",
        "bucket": "PROJECT",
        "tla_total_votes": 0,
        "tla_vote_share": 0,
        "pool_depth": 85.87,
        "pd_bribes": 0,
        "other_bribes": 0,
        "total_bribes": 0,
        "v_apr": "0 %",
        "adao_vote_vp": 0,
        "adao_vote_share": "0.00"
      },
      {
        "pool_name": "LUNA-SOLID LP",
        "dex": "Astroport",
        "bucket": "PROJECT",
        "tla_total_votes": 278500,
        "tla_vote_share": "1.4",
        "pool_depth": 13431.65,
        "pd_bribes": 40,
        "other_bribes": 0,
        "total_bribes": 40,
        "v_apr": "0 %",
        "adao_vote_vp": 43120,
        "adao_vote_share": "6.75"
      },
      {
        "pool_name": "LUNA-SOLID LP",
        "dex": "WhiteWhale",
        "bucket": "PROJECT",
        "tla_total_votes": 0,
        "tla_vote_share": 0,
        "pool_depth": 91.9,
        "pd_bribes": 40,
        "other_bribes": 0,
        "total_bribes": 40,
        "v_apr": "0 %",
        "adao_vote_vp": 0,
        "adao_vote_share": "0.00"
      },
      {
        "pool_name": "LUNA-SWTH LP",
        "dex": "Astroport",
        "bucket": "PROJECT",
        "tla_total_votes": 517960.00000000006,
        "tla_vote_share": "2.6",
        "pool_depth": 14609.85,
        "pd_bribes": 0,
        "other_bribes": 0,
        "total_bribes": 0,
        "v_apr": "0 %",
        "adao_vote_vp": 25420,
        "adao_vote_share": "3.98"
      },
      {
        "pool_name": "LUNA-SWTH LP",
        "dex": "WhiteWhale",
        "bucket": "PROJECT",
        "tla_total_votes": 0,
        "tla_vote_share": "0.0",
        "pool_depth": 1.53,
        "pd_bribes": 0,
        "other_bribes": 0,
        "total_bribes": 0,
        "v_apr": "0 %",
        "adao_vote_vp": 0,
        "adao_vote_share": "0.00"
      },
      {
        "pool_name": "LUNA-ampLUNA LP",
        "dex": "WhiteWhale",
        "bucket": "PROJECT",
        "tla_total_votes": 28980,
        "tla_vote_share": "0.1",
        "pool_depth": 118500,
        "pd_bribes": 150,
        "other_bribes": 0,
        "total_bribes": 150,
        "v_apr": "0 %",
        "adao_vote_vp": 0,
        "adao_vote_share": "0.00"
      },
      {
        "pool_name": "LUNA-ampLUNA LP",
        "dex": "Astroport",
        "bucket": "PROJECT",
        "tla_total_votes": 4960000,
        "tla_vote_share": "25.1",
        "pool_depth": 218520,
        "pd_bribes": 150,
        "other_bribes": 0,
        "total_bribes": 150,
        "v_apr": "0 %",
        "adao_vote_vp": 332150,
        "adao_vote_share": "51.99"
      },
      {
        "pool_name": "LUNA-boneLUNA LP",
        "dex": "Astroport",
        "bucket": "PROJECT",
        "tla_total_votes": 1980000,
        "tla_vote_share": "10.0",
        "pool_depth": 44980,
        "pd_bribes": 0,
        "other_bribes": 0,
        "total_bribes": 0,
        "v_apr": "0 %",
        "adao_vote_vp": 35010,
        "adao_vote_share": "5.48"
      },
      {
        "pool_name": "LUNA-boneLUNA LP",
        "dex": "WhiteWhale",
        "bucket": "PROJECT",
        "tla_total_votes": 563370,
        "tla_vote_share": "2.9",
        "pool_depth": 263020,
        "pd_bribes": 0,
        "other_bribes": 0,
        "total_bribes": 0,
        "v_apr": "0 %",
        "adao_vote_vp": 0,
        "adao_vote_share": "0.00"
      },
      {
        "pool_name": "LUNA-stLUNA LP",
        "dex": "Astroport",
        "bucket": "PROJECT",
        "tla_total_votes": 240590,
        "tla_vote_share": "1.2",
        "pool_depth": 5806.62,
        "pd_bribes": 0,
        "other_bribes": 0,
        "total_bribes": 0,
        "v_apr": "0 %",
        "adao_vote_vp": 0,
        "adao_vote_share": "0.00"
      },
      {
        "pool_name": "LUNA-stLUNA LP",
        "dex": "WhiteWhale",
        "bucket": "PROJECT",
        "tla_total_votes": 0,
        "tla_vote_share": "0.0",
        "pool_depth": 1.73,
        "pd_bribes": 0,
        "other_bribes": 0,
        "total_bribes": 0,
        "v_apr": "0 %",
        "adao_vote_vp": 0,
        "adao_vote_share": "0.00"
      },
      {
        "pool_name": "USDC-SOLID LP",
        "dex": "Astroport",
        "bucket": "PROJECT",
        "tla_total_votes": 2740000,
        "tla_vote_share": "13.9",
        "pool_depth": 98230,
        "pd_bribes": 0,
        "other_bribes": 78.33,
        "total_bribes": 78.33,
        "v_apr": "20.15 %",
        "adao_vote_vp": 29060,
        "adao_vote_share": "4.55"
      },
      {
        "pool_name": "USDC-SOLID LP",
        "dex": "WhiteWhale",
        "bucket": "PROJECT",
        "tla_total_votes": 23510,
        "tla_vote_share": "0.1",
        "pool_depth": 419.65,
        "pd_bribes": 0,
        "other_bribes": 0,
        "total_bribes": 0,
        "v_apr": "0 %",
        "adao_vote_vp": 0,
        "adao_vote_share": "0.00"
      },
      {
        "pool_name": "LUNA-ATOM LP",
        "dex": "Astroport",
        "bucket": "BLUECHIP",
        "tla_total_votes": 851860,
        "tla_vote_share": "4.5",
        "pool_depth": 30900,
        "pd_bribes": 50,
        "other_bribes": 0,
        "total_bribes": 50,
        "v_apr": "0 %",
        "adao_vote_vp": 79540,
        "adao_vote_share": "12.45"
      },
      {
        "pool_name": "LUNA-ATOM LP",
        "dex": "WhiteWhale",
        "bucket": "BLUECHIP",
        "tla_total_votes": 435650,
        "tla_vote_share": "2.3",
        "pool_depth": 11679.79,
        "pd_bribes": 50,
        "other_bribes": 0,
        "total_bribes": 50,
        "v_apr": "0 %",
        "adao_vote_vp": 0,
        "adao_vote_share": "0.00"
      },
      {
        "pool_name": "LUNA-INJ LP",
        "dex": "Astroport",
        "bucket": "BLUECHIP",
        "tla_total_votes": 64540.00000000001,
        "tla_vote_share": "0.3",
        "pool_depth": 1296.34,
        "pd_bribes": 0,
        "other_bribes": 0,
        "total_bribes": 0,
        "v_apr": "0 %",
        "adao_vote_vp": 0,
        "adao_vote_share": "0.00"
      },
      {
        "pool_name": "LUNA-INJ LP",
        "dex": "WhiteWhale",
        "bucket": "BLUECHIP",
        "tla_total_votes": 16260.000000000002,
        "tla_vote_share": "0.1",
        "pool_depth": 1817.7,
        "pd_bribes": 0,
        "other_bribes": 0,
        "total_bribes": 0,
        "v_apr": "0 %",
        "adao_vote_vp": 0,
        "adao_vote_share": "0.00"
      },
      {
        "pool_name": "LUNA-PAXG LP",
        "dex": "Astroport",
        "bucket": "BLUECHIP",
        "tla_total_votes": 4360000,
        "tla_vote_share": "23.0",
        "pool_depth": 77770,
        "pd_bribes": 20,
        "other_bribes": 65.9,
        "total_bribes": 85.9,
        "v_apr": "1.39-13.91 %",
        "adao_vote_vp": 0,
        "adao_vote_share": "0.00"
      },
      {
        "pool_name": "LUNA-wBNB.axl LP",
        "dex": "Astroport",
        "bucket": "BLUECHIP",
        "tla_total_votes": 0,
        "tla_vote_share": 0,
        "pool_depth": 688.18,
        "pd_bribes": 0,
        "other_bribes": 0,
        "total_bribes": 0,
        "v_apr": "0 %",
        "adao_vote_vp": 0,
        "adao_vote_share": "0.00"
      },
      {
        "pool_name": "LUNA-wBTC.atom LP",
        "dex": "Astroport",
        "bucket": "BLUECHIP",
        "tla_total_votes": 4059999.9999999995,
        "tla_vote_share": "21.4",
        "pool_depth": 83470,
        "pd_bribes": 0,
        "other_bribes": 0,
        "total_bribes": 0,
        "v_apr": "0 %",
        "adao_vote_vp": 150840,
        "adao_vote_share": "23.61"
      },
      {
        "pool_name": "LUNA-wBTC.axl LP",
        "dex": "Astroport",
        "bucket": "BLUECHIP",
        "tla_total_votes": 3320000,
        "tla_vote_share": "17.5",
        "pool_depth": 75120,
        "pd_bribes": 40,
        "other_bribes": 0,
        "total_bribes": 40,
        "v_apr": "0 %",
        "adao_vote_vp": 207190,
        "adao_vote_share": "32.43"
      },
      {
        "pool_name": "LUNA-wBTC.osmo LP",
        "dex": "WhiteWhale",
        "bucket": "BLUECHIP",
        "tla_total_votes": 1410000,
        "tla_vote_share": "7.5",
        "pool_depth": 30240,
        "pd_bribes": 0,
        "other_bribes": 0,
        "total_bribes": 0,
        "v_apr": "0 %",
        "adao_vote_vp": 0,
        "adao_vote_share": "0.00"
      },
      {
        "pool_name": "LUNA-wstETH LP",
        "dex": "Astroport",
        "bucket": "BLUECHIP",
        "tla_total_votes": 827760,
        "tla_vote_share": "4.4",
        "pool_depth": 16840,
        "pd_bribes": 30,
        "other_bribes": 0,
        "total_bribes": 30,
        "v_apr": "0 %",
        "adao_vote_vp": 37820,
        "adao_vote_share": "5.92"
      },
      {
        "pool_name": "LUNA-wstETH LP",
        "dex": "WhiteWhale",
        "bucket": "BLUECHIP",
        "tla_total_votes": 990000,
        "tla_vote_share": "5.3",
        "pool_depth": 24620,
        "pd_bribes": 30,
        "other_bribes": 0,
        "total_bribes": 30,
        "v_apr": "0 %",
        "adao_vote_vp": 0,
        "adao_vote_share": "0.00"
      },
      {
        "pool_name": "USDC-EURe LP",
        "dex": "Astroport",
        "bucket": "BLUECHIP",
        "tla_total_votes": 2600000,
        "tla_vote_share": "13.7",
        "pool_depth": 236300,
        "pd_bribes": 40,
        "other_bribes": 0,
        "total_bribes": 40,
        "v_apr": "0 %",
        "adao_vote_vp": 163490,
        "adao_vote_share": "25.59"
      },
      {
        "pool_name": "USDC-EURe LP",
        "dex": "WhiteWhale",
        "bucket": "BLUECHIP",
        "tla_total_votes": 0,
        "tla_vote_share": 0,
        "pool_depth": 4193.24,
        "pd_bribes": 40,
        "other_bribes": 0,
        "total_bribes": 40,
        "v_apr": "0 %",
        "adao_vote_vp": 0,
        "adao_vote_share": "0.00"
      },
      {
        "pool_name": "ATOM-stATOM LP",
        "dex": "Astroport",
        "bucket": "SINGLE",
        "tla_total_votes": 0,
        "tla_vote_share": 0,
        "pool_depth": 1527.26,
        "pd_bribes": 0,
        "other_bribes": 0,
        "total_bribes": 0,
        "v_apr": "0 %",
        "adao_vote_vp": 0,
        "adao_vote_share": "0.00"
      },
      {
        "pool_name": "ATOM-stATOM LP",
        "dex": "WhiteWhale",
        "bucket": "SINGLE",
        "tla_total_votes": 0,
        "tla_vote_share": "0.0",
        "pool_depth": 0.01,
        "pd_bribes": 0,
        "other_bribes": 0,
        "total_bribes": 0,
        "v_apr": "0 %",
        "adao_vote_vp": 0,
        "adao_vote_share": "0.00"
      },
      {
        "pool_name": "LUNA-arbLUNA LP",
        "dex": "Astroport",
        "bucket": "SINGLE",
        "tla_total_votes": 2040000,
        "tla_vote_share": "10.8",
        "pool_depth": 47160,
        "pd_bribes": 0,
        "other_bribes": 0,
        "total_bribes": 0,
        "v_apr": "0 %",
        "adao_vote_vp": 0,
        "adao_vote_share": "0.00"
      },
      {
        "pool_name": "LUNA-arbLUNA LP",
        "dex": "WhiteWhale",
        "bucket": "SINGLE",
        "tla_total_votes": 25690,
        "tla_vote_share": "0.1",
        "pool_depth": 3223.41,
        "pd_bribes": 0,
        "other_bribes": 0,
        "total_bribes": 0,
        "v_apr": "0 %",
        "adao_vote_vp": 0,
        "adao_vote_share": "0.00"
      },
      {
        "pool_name": "USDC-USDT LP",
        "dex": "Astroport",
        "bucket": "SINGLE",
        "tla_total_votes": 2089999.9999999998,
        "tla_vote_share": "11.1",
        "pool_depth": 224010,
        "pd_bribes": 70,
        "other_bribes": 0,
        "total_bribes": 70,
        "v_apr": "0 %",
        "adao_vote_vp": 80430,
        "adao_vote_share": "12.59"
      },
      {
        "pool_name": "USDC-USDT LP",
        "dex": "WhiteWhale",
        "bucket": "SINGLE",
        "tla_total_votes": 0.37,
        "tla_vote_share": "0.0",
        "pool_depth": 2973.8,
        "pd_bribes": 70,
        "other_bribes": 0,
        "total_bribes": 70,
        "v_apr": "0 %",
        "adao_vote_vp": 0,
        "adao_vote_share": "0.00"
      },
      {
        "pool_name": "ampCAPA",
        "dex": "Single",
        "bucket": "SINGLE",
        "tla_total_votes": 5120000,
        "tla_vote_share": "27.1",
        "pool_depth": 101680,
        "pd_bribes": 0,
        "other_bribes": 78.33,
        "total_bribes": 78.33,
        "v_apr": "1.08-10.81 %",
        "adao_vote_vp": 0,
        "adao_vote_share": "0.00"
      },
      {
        "pool_name": "ampROAR-ROAR LP",
        "dex": "Astroport",
        "bucket": "SINGLE",
        "tla_total_votes": 0,
        "tla_vote_share": 0,
        "pool_depth": 0.01,
        "pd_bribes": 0,
        "other_bribes": 0,
        "total_bribes": 0,
        "v_apr": "0 %",
        "adao_vote_vp": 0,
        "adao_vote_share": "0.00"
      },
      {
        "pool_name": "ampROAR-ROAR LP",
        "dex": "WhiteWhale",
        "bucket": "SINGLE",
        "tla_total_votes": 2360000,
        "tla_vote_share": "12.5",
        "pool_depth": 33070,
        "pd_bribes": 0,
        "other_bribes": 0,
        "total_bribes": 0,
        "v_apr": "0 %",
        "adao_vote_vp": 0,
        "adao_vote_share": "0.00"
      },
      {
        "pool_name": "wBTC.axl-wBTC.osmo LP",
        "dex": "Astroport",
        "bucket": "SINGLE",
        "tla_total_votes": 1870000,
        "tla_vote_share": "9.9",
        "pool_depth": 106310,
        "pd_bribes": 70,
        "other_bribes": 0,
        "total_bribes": 70,
        "v_apr": "0 %",
        "adao_vote_vp": 125150,
        "adao_vote_share": "19.59"
      },
      {
        "pool_name": "wBTC.osmo-wBTC.axl LP",
        "dex": "WhiteWhale",
        "bucket": "SINGLE",
        "tla_total_votes": 1980000,
        "tla_vote_share": "10.5",
        "pool_depth": 100230,
        "pd_bribes": 70,
        "other_bribes": 0,
        "total_bribes": 70,
        "v_apr": "0 %",
        "adao_vote_vp": 0,
        "adao_vote_share": "0.00"
      },
      {
        "pool_name": "wstETH-wETH.axl LP",
        "dex": "Astroport",
        "bucket": "SINGLE",
        "tla_total_votes": 3030000,
        "tla_vote_share": "16.1",
        "pool_depth": 64280,
        "pd_bribes": 0,
        "other_bribes": 0,
        "total_bribes": 0,
        "v_apr": "0 %",
        "adao_vote_vp": 162340,
        "adao_vote_share": "25.41"
      },
      {
        "pool_name": "xASTRO",
        "dex": "Single",
        "bucket": "SINGLE",
        "tla_total_votes": 341550,
        "tla_vote_share": "1.8",
        "pool_depth": 818050,
        "pd_bribes": 0,
        "other_bribes": 0,
        "total_bribes": 0,
        "v_apr": "0 %",
        "adao_vote_vp": 0,
        "adao_vote_share": "0.00"
      }
    ]
  },
  "bribes": {
    "epoch_range": "[160-163]",
    "is_pd_active": true,
    "items": [
      {
        "rank": 1,
        "bucket": "project",
        "pool": "AMPLUNA-LUNA",
        "score_percent": 55.44,
        "usd_amount": 150,
        "luna_amount": 1973.01
      },
      {
        "rank": 2,
        "bucket": "bluechip",
        "pool": "ATOM-LUNA",
        "score_percent": 24.17,
        "usd_amount": 50,
        "luna_amount": 657.67
      },
      {
        "rank": 3,
        "bucket": "bluechip",
        "pool": "EURE-USDC",
        "score_percent": 21.51,
        "usd_amount": 40,
        "luna_amount": 526.14
      },
      {
        "rank": 4,
        "bucket": "bluechip",
        "pool": "LUNA-WBTC.AXL",
        "score_percent": 20.95,
        "usd_amount": 40,
        "luna_amount": 526.14
      },
      {
        "rank": 5,
        "bucket": "bluechip",
        "pool": "LUNA-WBTC",
        "score_percent": 16.75,
        "usd_amount": 40,
        "luna_amount": 526.14
      },
      {
        "rank": 6,
        "bucket": "project",
        "pool": "FUEL-LUNA",
        "score_percent": 10.21,
        "usd_amount": 50,
        "luna_amount": 657.67
      },
      {
        "rank": 7,
        "bucket": "project",
        "pool": "ASTRO-LUNA",
        "score_percent": 9.84,
        "usd_amount": 50,
        "luna_amount": 657.67
      },
      {
        "rank": 8,
        "bucket": "single",
        "pool": "USDC-USDT",
        "score_percent": 8.6,
        "usd_amount": 70,
        "luna_amount": 920.74
      },
      {
        "rank": 9,
        "bucket": "project",
        "pool": "LUNA-SOLID",
        "score_percent": 8.23,
        "usd_amount": 40,
        "luna_amount": 526.14
      },
      {
        "rank": 10,
        "bucket": "bluechip",
        "pool": "LUNA-WSTETH",
        "score_percent": 7.29,
        "usd_amount": 30,
        "luna_amount": 394.6
      },
      {
        "rank": 11,
        "bucket": "bluechip",
        "pool": "LUNA-PAXG",
        "score_percent": 7.08,
        "usd_amount": 20,
        "luna_amount": 263.07
      },
      {
        "rank": 12,
        "bucket": "single",
        "pool": "WBTC.AXL-WBTC.OSMO",
        "score_percent": 6.72,
        "usd_amount": 70,
        "luna_amount": 920.74
      }
    ]
  },
  "locks": {
    "adao_voting_power": 638880,
    "power_factor": 10,
    "underlying_assets": "63.88K LUNA",
    "items": [
      {
        "id": "600",
        "amount": 27290,
        "asset": "arbLUNA",
        "usd_value": 4910.76,
        "voting_power": 631570,
        "status": "Max Lock (Auto)"
      },
      {
        "id": "711",
        "amount": 413.03,
        "asset": "ampLUNA",
        "usd_value": 54.34,
        "voting_power": 7316.76,
        "status": "Max Lock (Auto)"
      }
    ]
  },
  "votion_optimization": {
    "ratios": {
      "arb_luna": 2.4359,
      "amp_luna": 1.8668
    },
    "pools": [
      {
        "id": "arbLUNA - Max",
        "asset": "arbLUNA",
        "duration": "Max",
        "tvl_token": 161570.58,
        "tvl_usd": 29073.23,
        "apy": "94.78%",
        "rewards": 181.34,
        "epoch": "160",
        "votes": [
          {
            "b": "Stable",
            "n": "LUNA-USDC LP",
            "f": 100,
            "t": 100
          },
          {
            "b": "Project",
            "n": "FUEL-LUNA LP",
            "f": 22.58,
            "t": 30.45
          },
          {
            "b": "Project",
            "n": "CAPA-LUNA LP",
            "f": 21.37,
            "t": 35.99
          },
          {
            "b": "Project",
            "n": "USDC-SOLID LP",
            "f": 15.07,
            "t": 33.56
          },
          {
            "b": "Bluechip",
            "n": "LUNA-PAXG.atom LP",
            "f": 33.38,
            "t": 100
          },
          {
            "b": "Single",
            "n": "ampCAPA",
            "f": 0,
            "t": 100
          }
        ]
      },
      {
        "id": "ampLUNA - Max",
        "asset": "ampLUNA",
        "duration": "Max",
        "tvl_token": 42943.53,
        "tvl_usd": 5650.33,
        "apy": "92.96%",
        "rewards": 50.57,
        "epoch": "160",
        "votes": [
          {
            "b": "Stable",
            "n": "LUNA-USDC LP",
            "f": 100,
            "t": 100
          },
          {
            "b": "Project",
            "n": "FUEL-LUNA LP",
            "f": 66.48,
            "t": 54.25
          },
          {
            "b": "Project",
            "n": "CAPA-LUNA LP",
            "f": 26.97,
            "t": 23.58
          },
          {
            "b": "Project",
            "n": "USDC-SOLID LP",
            "f": 6.55,
            "t": 22.17
          },
          {
            "b": "Bluechip",
            "n": "LUNA-PAXG.atom LP",
            "f": 100,
            "t": 100
          },
          {
            "b": "Single",
            "n": "ampCAPA",
            "f": 16.68,
            "t": 100
          }
        ]
      },
      {
        "id": "arbLUNA - 1 Week",
        "asset": "arbLUNA",
        "duration": "1 Week",
        "tvl_token": 714.18,
        "tvl_usd": 128.51,
        "apy": "41.45%",
        "rewards": 0.12,
        "epoch": "160",
        "votes": [
          {
            "b": "Project",
            "n": "USDC-SOLID LP",
            "f": 0,
            "t": 100
          },
          {
            "b": "Bluechip",
            "n": "LUNA-PAXG.atom LP",
            "f": 0,
            "t": 100
          },
          {
            "b": "Single",
            "n": "ampCAPA",
            "f": 0,
            "t": 100
          }
        ]
      },
      {
        "id": "ampLUNA - 1 Week",
        "asset": "ampLUNA",
        "duration": "1 Week",
        "tvl_token": 116.9,
        "tvl_usd": 15.38,
        "apy": "33.26%",
        "rewards": 0.02,
        "epoch": "160",
        "votes": []
      },
      {
        "id": "ampLUNA - 3 Months",
        "asset": "ampLUNA",
        "duration": "3 Months",
        "tvl_token": 0.5,
        "tvl_usd": 0.07,
        "apy": "32.97%",
        "rewards": 0,
        "epoch": "160",
        "votes": []
      },
      {
        "id": "arbLUNA - 3 Months",
        "asset": "arbLUNA",
        "duration": "3 Months",
        "tvl_token": 0,
        "tvl_usd": 0,
        "apy": "33.20%",
        "rewards": 0,
        "epoch": "160",
        "votes": []
      }
    ]
  }
}